deepl/__init__.py
deepl/__main__.py
deepl/api_data.py
deepl/deepl_client.py
deepl/exceptions.py
deepl/http_client.py
deepl/py.typed
deepl/translator.py
deepl/util.py
deepl/version.py
deepl-1.25.0.dist-info/LICENSE
deepl-1.25.0.dist-info/METADATA
deepl-1.25.0.dist-info/WHEEL
deepl-1.25.0.dist-info/entry_points.txt
deepl-1.25.0.dist-info/RECORD
