Metadata-Version: 2.3
Name: deepl
Version: 1.25.0
Summary: Python library for the DeepL API.
License: MIT
Author: DeepL SE
Author-email: python-api@deepl.com
Requires-Python: >=3.9,<4
Classifier: Development Status :: 5 - Production/Stable
Classifier: Intended Audience :: Developers
Classifier: License :: OSI Approved :: MIT License
Classifier: Operating System :: OS Independent
Classifier: Programming Language :: Python :: 3
Classifier: Programming Language :: Python :: 3.9
Classifier: Programming Language :: Python :: 3.10
Classifier: Programming Language :: Python :: 3.11
Classifier: Programming Language :: Python :: 3.12
Classifier: Programming Language :: Python :: 3.13
Classifier: Programming Language :: Python :: 3.6
Classifier: Topic :: Software Development :: Libraries :: Python Modules
Provides-Extra: keyring
Requires-Dist: keyring (>=23.4.1,<24.0.0) ; extra == "keyring"
Requires-Dist: requests (>=2.32.4)
Project-URL: Bug Tracker, https://github.com/DeepLcom/deepl-python/issues
Project-URL: Documentation, https://www.deepl.com/docs-api/
Project-URL: Repository, https://github.com/DeepLcom/deepl-python
